listproject/__init__.py
listproject/celery.py
listproject/settings.py
listproject/urls.py
listproject/wsgi.py
shoplistapp-2.0.0.data/scripts/manage.py
shoppinglist/__init__.py
shoppinglist/admin.py
shoppinglist/forms.py
shoppinglist/models.py
shoppinglist/setup.py
shoppinglist/test_app.py
shoppinglist/urls.py
shoppinglist/views.py
shoppinglist/migrations/0001_initial.py
shoppinglist/migrations/0002_remove_shoppinglist_image.py
shoppinglist/migrations/0003_shoppinglist_created_at.py
shoppinglist/migrations/0004_shoppinglist_price.py
shoppinglist/migrations/0005_auto_20190703_0758.py
shoppinglist/migrations/0006_auto_20190703_1016.py
shoppinglist/migrations/0007_auto_20190703_1022.py
shoppinglist/migrations/0008_auto_20190703_1025.py
shoppinglist/migrations/0009_auto_20190703_1130.py
shoppinglist/migrations/0010_auto_20190703_1148.py
shoppinglist/migrations/0011_auto_20190703_1149.py
shoppinglist/migrations/0012_auto_20190704_1123.py
shoppinglist/migrations/0013_auto_20190705_0738.py
shoppinglist/migrations/0014_auto_20190705_0742.py
shoppinglist/migrations/0015_auto_20190705_0743.py
shoppinglist/migrations/0016_auto_20190705_0745.py
shoppinglist/migrations/0017_auto_20190705_0746.py
shoppinglist/migrations/0018_auto_20190705_0753.py
shoppinglist/migrations/0019_auto_20190705_0755.py
shoppinglist/migrations/0020_auto_20190705_1046.py
shoppinglist/migrations/0021_auto_20190705_1048.py
shoppinglist/migrations/0022_auto_20190705_1212.py
shoppinglist/migrations/0023_auto_20190705_1213.py
shoppinglist/migrations/0024_auto_20190707_1127.py
shoppinglist/migrations/0025_auto_20190708_0923.py
shoppinglist/migrations/0026_auto_20190710_0639.py
shoppinglist/migrations/__init__.py
shoplistapp-2.0.0.dist-info/LICENSE
shoplistapp-2.0.0.dist-info/METADATA
shoplistapp-2.0.0.dist-info/WHEEL
shoplistapp-2.0.0.dist-info/top_level.txt
shoplistapp-2.0.0.dist-info/RECORD
